bpda/__init__.py
bpda/bpda.py
bpda-2020.4.18.dist-info/LICENSE
bpda-2020.4.18.dist-info/METADATA
bpda-2020.4.18.dist-info/WHEEL
bpda-2020.4.18.dist-info/top_level.txt
bpda-2020.4.18.dist-info/RECORD
