Metadata-Version: 2.1
Name: bpda
Version: 2020.4.18
Summary: BingPanDevApi.py: Make Old Bing Pics Can Access
Home-page: http://rdpstudio.top
Author: Jack
Author-email: admin@rdpstudo.top
Maintainer: Jack
Maintainer-email: admin@rdpstudo.top
License: Public domain
Platform: any
Requires-Dist: requests
